LICENSE
README.md
setup.py
dearpygui_extend/__init__.py
dearpygui_extend/file_browser.py
dearpygui_extend/layout.py
dearpygui_extend/movable_group.py
dearpygui_extend.egg-info/PKG-INFO
dearpygui_extend.egg-info/SOURCES.txt
dearpygui_extend.egg-info/dependency_links.txt
dearpygui_extend.egg-info/requires.txt
dearpygui_extend.egg-info/top_level.txt