Metadata-Version: 2.1
Name: dearpygui_extend
Version: 0.1.5
Summary: Extensions and custom widgets for Dear Py GUI
Home-page: https://github.com/fabriciochamon/DearPyGui_Extend
Author: Fabricio Chamon
Author-email: fabricio.chamon@gmail.com
License: MIT
Classifier: License :: OSI Approved :: MIT License
Classifier: Programming Language :: Python :: 3.10
Requires-Python: >=3.10
License-File: LICENSE
Requires-Dist: dearpygui>=1.9.1
Requires-Dist: Fileseq>=1.15.2
Requires-Dist: future>=0.18.3
